{
  "updated_at": "2025-02-09 09:55:41",
  "posts": [
    {
      "id": "17916634743059573",
      "url": "https://www.instagram.com/p/17916634743059573/",
      "cover": "https://scontent-iad3-1.cdninstagram.com/v/t51.75761-15/476465331_18488465395058696_3395353538316330310_n.jpg?stp=dst-jpg_e35_tt6&_nc_cat=101&ccb=1-7&_nc_sid=18de74&_nc_ohc=HtnZwUWDkPYQ7kNvgHAcO4T&_nc_oc=Adgx71jFWlEifTTVbd7RNZ6UNucUmVebR16aJUAHK49u6NgQ5Zi6PlKT7Gtvbq6Rh1I&_nc_zt=23&_nc_ht=scontent-iad3-1.cdninstagram.com&edm=ANo9K5cEAAAA&_nc_gid=AOdK-87z7OhfZk0b-O0W-aN&oh=00_AYB__i21ygzOpi2f7lUYkMrfhwJMFcBcE2iUQaU9x0johQ&oe=67AE2F17",
      "tags": [
        "any_step_one_joy",
        "green-city-complex",
        "Ramsar",
        "گردشگری",
        "نمایشگاه",
        "تهران",
        "خزر_تا_البرز",
        "هر_قدم_یک_شادی",
        "نمایشگاه_بین_المللی_تهران",
        "ایرانگردی",
        "توریسم",
        "توریست",
        "هتل",
        "تله_کابین_رامسر",
        "شهر_سبز_رامسر",
        "کارتینگ",
        "هتل_بام_سبز_رامسر",
        "ورزش_آبی",
        "شهربازی",
        "اتاق_فرار",
        "پینتبال",
        "زیپلاین"
      ]
    },
    {
      "id": "18040137347103475",
      "url": "https://www.instagram.com/p/18040137347103475/",
      "cover": "https://scontent-iad3-1.cdninstagram.com/v/t51.29350-15/460201274_1883683168821950_3516472473556352224_n.jpg?stp=dst-jpg_e35_tt6&_nc_cat=108&ccb=1-7&_nc_sid=18de74&_nc_ohc=989XTvoLgzEQ7kNvgHsZ5-O&_nc_oc=Adhr6eOINYRM2VLs_2d_s3qruKfJqTLkEyChPnkVhLRXNhNSf_2ovrmpHYNE2fdIt1M&_nc_zt=23&_nc_ht=scontent-iad3-1.cdninstagram.com&edm=ANo9K5cEAAAA&_nc_gid=AOdK-87z7OhfZk0b-O0W-aN&oh=00_AYCMh_9EVB4LdOMovjnIfEEtRYwASIsBB_8lr9RxTM7o7g&oe=67AE2014",
      "tags": [
        "شمال_بهشت_ایران",
        "رامسرگردی",
        "شمالگردی",
        "شادی_کن",
        "رامسر",
        "تله_کابین_رامسر",
        "جانمونی",
        "شهرسبزرامسر",
        "هتل"
      ]
    },
    {
      "id": "17874087183163799",
      "url": "https://www.instagram.com/p/17874087183163799/",
      "cover": "https://scontent-iad3-2.cdninstagram.com/v/t51.29350-15/460330474_548476274510906_8853307123947699350_n.jpg?stp=dst-jpg_e35_tt6&_nc_cat=103&ccb=1-7&_nc_sid=18de74&_nc_ohc=PAZk6l9GWDMQ7kNvgHCwqPD&_nc_oc=AdiVgCrSMV3jvhZAJ2ZBRVneX7vbuh72xuWHixdWHS132P8Ioz3Tfnhzie3WbiuJAsY&_nc_zt=23&_nc_ht=scontent-iad3-2.cdninstagram.com&edm=ANo9K5cEAAAA&_nc_gid=AOdK-87z7OhfZk0b-O0W-aN&oh=00_AYBn0UMXfKHj5woml-TBgG4QtND8v8sYpgKngrNjvLCvSQ&oe=67AE187B",
      "tags": [
        "شمالگردی",
        "تله_کابین",
        "شمال_بهشت_ایران",
        "کجابریم",
        "رامسر",
        "جانمونی",
        "تله_کابین_رامسر"
      ]
    },
    {
      "id": "17930438951933596",
      "url": "https://www.instagram.com/p/17930438951933596/",
      "cover": "https://scontent-iad3-2.cdninstagram.com/v/t51.29350-15/460276558_2737129363114675_8542869754853770216_n.jpg?stp=dst-jpg_e35_tt6&_nc_cat=105&ccb=1-7&_nc_sid=18de74&_nc_ohc=ZvtoDMfhUI0Q7kNvgHyfSfh&_nc_oc=AdgpKQuU9Gswl38i_ARQzoIgOUhYWkWi9qUE2QyIE4JNIL7IFuddZiZ6vjoqM8tasVQ&_nc_zt=23&_nc_ht=scontent-iad3-2.cdninstagram.com&edm=ANo9K5cEAAAA&_nc_gid=AOdK-87z7OhfZk0b-O0W-aN&oh=00_AYC6dfT1zM8pah32M0GsX5USufzsWuWYhsu9cK8MnGH11g&oe=67AE2F40",
      "tags": [
        "ایرانگردی",
        "توریستی_گردشگری",
        "تله_کابین",
        "شادی",
        "رامسر",
        "جانمونی",
        "تله_کابین_رامسر",
        "شهرسبزرامسر"
      ]
    },
    {
      "id": "18058081591705983",
      "url": "https://www.instagram.com/p/18058081591705983/",
      "cover": "https://scontent-iad3-2.cdninstagram.com/v/t51.29350-15/460217878_532884209141152_4803535556126300779_n.jpg?stp=dst-jpg_e35_tt6&_nc_cat=106&ccb=1-7&_nc_sid=18de74&_nc_ohc=9qhARTvDIWQQ7kNvgFqBJEx&_nc_oc=Adj2Pmn1SiJJdCRrfGMMPTshIKHom3QJZo8qqBMyGtBUCKuycGFRsDhRBezScqDU5yg&_nc_zt=23&_nc_ht=scontent-iad3-2.cdninstagram.com&edm=ANo9K5cEAAAA&_nc_gid=AOdK-87z7OhfZk0b-O0W-aN&oh=00_AYDMhKhOCUFBoUhCX9F7-7iMNCRltPmGjUTqt79OEefdSw&oe=67AE2C17",
      "tags": [
        "سفر_ارزان",
        "هتل",
        "شهربازی",
        "شادی_کن",
        "رامسر",
        "جانمونی",
        "شهرسبزرامسر",
        "هتل_بام_سبز_رامسر"
      ]
    },
    {
      "id": "18000040295506443",
      "url": "https://www.instagram.com/p/18000040295506443/",
      "cover": "https://scontent-iad3-1.cdninstagram.com/v/t51.29350-15/459595286_1919637675188891_7674517221436330263_n.jpg?stp=dst-jpg_e35_tt6&_nc_cat=108&ccb=1-7&_nc_sid=18de74&_nc_ohc=i_irZqxNFUkQ7kNvgEEIlEx&_nc_oc=AdiDaYkZlrzQO0jJnBtojHH2pB8uktQg20hi2p9OjDVm6zsFhvtqXHrgh_aFNxnhdaY&_nc_zt=23&_nc_ht=scontent-iad3-1.cdninstagram.com&edm=ANo9K5cEAAAA&_nc_gid=AOdK-87z7OhfZk0b-O0W-aN&oh=00_AYBunXFwDiva1rVD2s0RXYZ2Hz3yxNrb6QgZn7dTJVezPQ&oe=67AE2FAF",
      "tags": [
        "ایرانگردی",
        "گردشگری",
        "کوه",
        "دریا",
        "تله_کابین",
        "شهربازی",
        "هیجان",
        "باحال",
        "رامسر",
        "تله_کابین",
        "رامسر",
        "کجابریم",
        "جانمونی"
      ]
    },
    {
      "id": "18031269011218470",
      "url": "https://www.instagram.com/p/18031269011218470/",
      "cover": "https://scontent-iad3-1.cdninstagram.com/v/t51.29350-15/459358154_1326926468285666_4586624397049661666_n.jpg?stp=dst-jpg_e35_tt6&_nc_cat=108&ccb=1-7&_nc_sid=18de74&_nc_ohc=yapQWFY2vL4Q7kNvgH5c11b&_nc_oc=AdguB_-XWAkzi2Uysc393kpJce5PrvRsiBK7OooitfYIkuLOFmbnNlgOkk1J_2RBWlE&_nc_zt=23&_nc_ht=scontent-iad3-1.cdninstagram.com&edm=ANo9K5cEAAAA&_nc_gid=AOdK-87z7OhfZk0b-O0W-aN&oh=00_AYBtbzNflL5SoravLx1-DJD094uaB3eyIauvOC-sgsXRbQ&oe=67AE036B",
      "tags": [
        "هتل",
        "اقامت",
        "شهربازی",
        "جت",
        "آروم",
        "هیجانی",
        "رامسر",
        "جانمونی",
        "جشنواره",
        "هتل_بام_رامسر",
        "تله_کابین_رامسر",
        "تله_کابین_رامسر"
      ]
    },
    {
      "id": "18029974451464626",
      "url": "https://www.instagram.com/p/18029974451464626/",
      "cover": "https://scontent-iad3-2.cdninstagram.com/v/t51.29350-15/459380829_1230585057966791_9213039037849991578_n.jpg?stp=dst-jpg_e35_tt6&_nc_cat=100&ccb=1-7&_nc_sid=18de74&_nc_ohc=FYaPD52kZIcQ7kNvgF57ArE&_nc_oc=Adgi7DiWyYEzl77bFQNiLgdFiPV_EIGjXejjVKGI--Ef_Afmz0qN-bDIvaAvgEyhlsQ&_nc_zt=23&_nc_ht=scontent-iad3-2.cdninstagram.com&edm=ANo9K5cEAAAA&_nc_gid=AOdK-87z7OhfZk0b-O0W-aN&oh=00_AYDZXscf3PQKUwE4ZIYKQUAwJOtny_1QqnbJLggT1fiF7w&oe=67AE29E4",
      "tags": [
        "شمالگردی",
        "ایرانگردی#توریستی",
        "تفریحی",
        "شادی",
        "خوشی",
        "رامسر",
        "جانمونی",
        "شهرسبزرامسر",
        "تله_کابین_رامسر"
      ]
    },
    {
      "id": "18034690294979564",
      "url": "https://www.instagram.com/p/18034690294979564/",
      "cover": "https://scontent-iad3-1.cdninstagram.com/v/t51.29350-15/461112340_451107921414882_1489434891362976137_n.jpg?stp=dst-jpg_e35_tt6&_nc_cat=108&ccb=1-7&_nc_sid=18de74&_nc_ohc=uXPVnM36CQsQ7kNvgF0XCXJ&_nc_oc=AdgPm92_FCoxwyOgwcbPCxDIMFZ5df59YaCqKCkhC5XGrfXJRUAB936fJcVydPn-P64&_nc_zt=23&_nc_ht=scontent-iad3-1.cdninstagram.com&edm=ANo9K5cEAAAA&_nc_gid=AOdK-87z7OhfZk0b-O0W-aN&oh=00_AYBfA5XMnPCQwQXJgKJSNoHsApjlGHzvQU3c6eEnB9RZ5Q&oe=67AE1633",
      "tags": []
    },
    {
      "id": "18061731154640151",
      "url": "https://www.instagram.com/p/18061731154640151/",
      "cover": "https://scontent-iad3-2.cdninstagram.com/v/t51.29350-15/459273244_699567089054557_4065760040486034502_n.jpg?stp=dst-jpg_e35_tt6&_nc_cat=100&ccb=1-7&_nc_sid=18de74&_nc_ohc=Blj0borbJbQQ7kNvgEZ1Rrc&_nc_oc=Adh2746rYPbdW08--6cyAk5-9VgKX0XY7LiFqp9gmGk8ImHvJrKXdzxnX_N_U-IkNdc&_nc_zt=23&_nc_ht=scontent-iad3-2.cdninstagram.com&edm=ANo9K5cEAAAA&_nc_gid=AOdK-87z7OhfZk0b-O0W-aN&oh=00_AYBGAiZjuxgihLpKS3tQkqfCC7tVWRJH1c3ef-Hm1zAMRA&oe=67AE0E2D",
      "tags": [
        "جانمونی",
        "کجابریم",
        "تله_کابین"
      ]
    }
  ]
}